{
  "version": "7",
  "dialect": "postgresql",
  "entries": [
    {
      "idx": 0,
      "version": "7",
      "when": 1765080188586,
      "tag": "0000_last_ozymandias",
      "breakpoints": true
    },
    {
      "idx": 1,
      "version": "7",
      "when": 1765111863545,
      "tag": "0001_special_alice",
      "breakpoints": true
    },
    {
      "idx": 2,
      "version": "7",
      "when": 1765248002732,
      "tag": "0002_dusty_pete_wisdom",
      "breakpoints": true
    },
    {
      "idx": 3,
      "version": "7",
      "when": 1765251658787,
      "tag": "0003_deep_leader",
      "breakpoints": true
    },
    {
      "idx": 4,
      "version": "7",
      "when": 1765416814477,
      "tag": "0004_tidy_spiral",
      "breakpoints": true
    },
    {
      "idx": 5,
      "version": "7",
      "when": 1765455738096,
      "tag": "0005_smart_inertia",
      "breakpoints": true
    },
    {
      "idx": 6,
      "version": "7",
      "when": 1765509352157,
      "tag": "0006_lush_queen_noir",
      "breakpoints": true
    }
  ]
}